pysantec/__about__.py
pysantec/__init__.py
pysantec/logger.py
pysantec/drivers/__init__.py
pysantec/drivers/dll_manager.py
pysantec/instruments/__init__.py
pysantec/instruments/base_instrument.py
pysantec/instruments/daq_instrument.py
pysantec/instruments/instrument_manager.py
pysantec/instruments/mpm_instrument.py
pysantec/instruments/tsl_instrument.py
pysantec/instruments/wrapper/__init__.py
pysantec/instruments/wrapper/exceptions.py
pysantec/instruments/wrapper/instrument_wrapper.py
pysantec/instruments/wrapper/santec_communication_wrapper.py
pysantec/instruments/wrapper/santec_wrapper.py
pysantec/instruments/wrapper/enumerations/__init__.py
pysantec/instruments/wrapper/enumerations/connection_enums.py
pysantec/instruments/wrapper/enumerations/mpm_enums.py
pysantec/instruments/wrapper/enumerations/tsl_enums.py
pysantec/measurements/__init__.py
pysantec/measurements/single_measurement_operation.py
pysantec-0.2.0.dist-info/licenses/LICENSE
pysantec-0.2.0.dist-info/METADATA
pysantec-0.2.0.dist-info/WHEEL
pysantec-0.2.0.dist-info/top_level.txt
pysantec-0.2.0.dist-info/RECORD
