Metadata-Version: 2.4
Name: pysantec
Version: 0.2.0
Summary: Python Package for Santec IL and PDL Swept Test System
Author: Santec Holdings Corporation
Maintainer: Rakshith P J
License-Expression: MIT
Project-URL: Homepage, https://github.com/santec-corporation/pysantec
Project-URL: Repository, https://github.com/santec-corporation/pysantec
Project-URL: ChangeLog, https://github.com/santec-corporation/pysantec/blob/main/CHANGELOG.md
Classifier: Development Status :: 4 - Beta
Classifier: Intended Audience :: Science/Research
Classifier: Intended Audience :: Developers
Classifier: Operating System :: Microsoft :: Windows
Classifier: Topic :: Scientific/Engineering :: Physics
Classifier: Topic :: Software Development :: Libraries :: Python Modules
Classifier: Programming Language :: Python :: 3
Classifier: Programming Language :: Python :: 3.10
Classifier: Programming Language :: Python :: 3.11
Classifier: Programming Language :: Python :: 3.12
Requires-Python: >=3.10
License-File: LICENSE
Dynamic: license-file
